tap_clinicaltrials/__init__.py
tap_clinicaltrials/__main__.py
tap_clinicaltrials/discover.py
tap_clinicaltrials/streams.py
tap_clinicaltrials/tap.py
tap_clinicaltrials-0.2.9.dist-info/METADATA
tap_clinicaltrials-0.2.9.dist-info/WHEEL
tap_clinicaltrials-0.2.9.dist-info/entry_points.txt
tap_clinicaltrials-0.2.9.dist-info/licenses/LICENSE
tap_clinicaltrials-0.2.9.dist-info/RECORD
