Metadata-Version: 2.4
Name: tap-clinicaltrials
Version: 0.2.9
Summary: `tap-clinicaltrials` is a Singer tap for ClinicalTrials.gov, built with the Meltano SDK for Singer Taps.
Project-URL: Documentation, https://github.com/edgarrmondragon/tap-clinicaltrials#readme
Project-URL: Homepage, https://github.com/edgarrmondragon/tap-clinicaltrials
Project-URL: Repository, https://github.com/edgarrmondragon/tap-clinicaltrials
Author-email: Edgar Ramírez-Mondragón <edgarrmondragon@hey.com>
Maintainer-email: Edgar Ramírez-Mondragón <edgarrmondragon@hey.com>
License-Expression: Apache-2.0
License-File: LICENSE
Keywords: ClinicalTrials.gov,ELT,singer.io
Classifier: Programming Language :: Python :: 3 :: Only
Classifier: Programming Language :: Python :: 3.10
Classifier: Programming Language :: Python :: 3.11
Classifier: Programming Language :: Python :: 3.12
Classifier: Programming Language :: Python :: 3.13
Classifier: Programming Language :: Python :: 3.14
Requires-Python: >=3.10
Requires-Dist: requests-cache<2,>=1
Requires-Dist: requests<3,>=2
Requires-Dist: singer-sdk~=0.51.0
